logovm/__init__.py
logovm/__main__.py
logovm/errors.py
logovm/extensions.py
logovm/loader.py
logovm/logoos.py
logovm/machine.py
logovm/turtleos.py
logovm-0.2.1.dist-info/COPYING
logovm-0.2.1.dist-info/METADATA
logovm-0.2.1.dist-info/WHEEL
logovm-0.2.1.dist-info/entry_points.txt
logovm-0.2.1.dist-info/top_level.txt
logovm-0.2.1.dist-info/RECORD
