Metadata-Version: 2.1
Name: logovm
Version: 0.2.1
Summary: A collection of tools to teach compiler design and implementation.
Author-email: Rafael Guterres Jeffman <rafasgj@gmail.com>
License: GNU GENERAL PUBLIC LICENSE
Project-URL: homepage, https://github.com/rafasgj/logovm
Project-URL: repository, https://github.com/rafasgj/logovm
Project-URL: issues, https://github.com/rafasgj/logovm/issues
Keywords: teaching,compiler,Logo
Classifier: Development Status :: 4 - Beta
Classifier: Intended Audience :: Education
Classifier: License :: OSI Approved :: GNU General Public License v3 or later (GPLv3+)
Requires-Python: >=3.10
License-File: COPYING
Provides-Extra: dev
Requires-Dist: logovm[lint,test] ; extra == 'dev'
Provides-Extra: graphic
Requires-Dist: pillow ; extra == 'graphic'
Provides-Extra: jpg
Requires-Dist: pillow ; extra == 'jpg'
Provides-Extra: lint
Requires-Dist: black ; extra == 'lint'
Requires-Dist: pylint ; extra == 'lint'
Requires-Dist: flake8 ; extra == 'lint'
Requires-Dist: pydocstyle ; extra == 'lint'
Provides-Extra: png
Requires-Dist: pillow ; extra == 'png'
Provides-Extra: test
Requires-Dist: pytest ; extra == 'test'
Requires-Dist: pytest-cov ; extra == 'test'
Requires-Dist: coverage ; extra == 'test'
Requires-Dist: tox ; extra == 'test'
